open_hue/__init__.py
open_hue/sdk.py
open_hue/hooks/__init__.py
open_hue/hooks/hook.py
open_hue/models/__init__.py
open_hue/models/action_get.py
open_hue/models/action_post.py
open_hue/models/alert.py
open_hue/models/authenticate_request.py
open_hue/models/base.py
open_hue/models/bridge_get.py
open_hue/models/bridge_home_get.py
open_hue/models/bridge_put.py
open_hue/models/color.py
open_hue/models/color_palette_get.py
open_hue/models/color_temperature.py
open_hue/models/color_temperature_delta.py
open_hue/models/color_temperature_palette_post.py
open_hue/models/create_room_ok_response.py
open_hue/models/create_scene_ok_response.py
open_hue/models/create_zone_ok_response.py
open_hue/models/delete_device_ok_response.py
open_hue/models/delete_room_ok_response.py
open_hue/models/delete_scene_ok_response.py
open_hue/models/delete_zone_ok_response.py
open_hue/models/device_get.py
open_hue/models/device_power_get.py
open_hue/models/device_put.py
open_hue/models/dimming.py
open_hue/models/dimming_delta.py
open_hue/models/dynamics.py
open_hue/models/dynamics_2.py
open_hue/models/effects.py
open_hue/models/error.py
open_hue/models/gamut_position.py
open_hue/models/get_bridge_home_ok_response.py
open_hue/models/get_bridge_homes_ok_response.py
open_hue/models/get_bridge_ok_response.py
open_hue/models/get_bridges_ok_response.py
open_hue/models/get_device_ok_response.py
open_hue/models/get_device_power_ok_response.py
open_hue/models/get_device_powers_ok_response.py
open_hue/models/get_devices_ok_response.py
open_hue/models/get_grouped_light_ok_response.py
open_hue/models/get_grouped_lights_ok_response.py
open_hue/models/get_light_level_ok_response.py
open_hue/models/get_light_levels_ok_response.py
open_hue/models/get_light_ok_response.py
open_hue/models/get_lights_ok_response.py
open_hue/models/get_motion_sensor_ok_response.py
open_hue/models/get_motion_sensors_ok_response.py
open_hue/models/get_resources_ok_response.py
open_hue/models/get_room_ok_response.py
openhue_client-1.0.0.dist-info/LICENSE
openhue_client-1.0.0.dist-info/METADATA
openhue_client-1.0.0.dist-info/WHEEL
openhue_client-1.0.0.dist-info/top_level.txt
openhue_client-1.0.0.dist-info/RECORD
