Metadata-Version: 2.1
Name: openhue-client
Version: 1.0.0
Summary: See [openhue/openhue-api](https://github.com/openhue/openhue-api)
License: MIT
Requires-Python: >=3.7
License-File: LICENSE
Requires-Dist: requests >=2.31.0
